i4t/__init__.py
i4t/cli/__init__.py
i4t/cli/config.py
i4t/client/__init__.py
i4t/client/applet.py
i4t/client/channel.py
i4t/client/client.py
i4t/client/topic.py
i4t/core/__init__.py
i4t/core/common.py
i4t/core/firmware.py
i4t/core/instancing.py
i4t/core/provisioning.py
i4t/core/session.py
i4t/core/utilites.py
i4t/protobuf/Firmware_pb2.py
i4t/protobuf/Instancing_pb2.py
i4t/protobuf/Provisioning_pb2.py
i4t/protobuf/Session_pb2.py
i4t/protobuf/__init__.py
i4t/protobuf/common_pb2.py
i4t/protobuf/protobuf/Instancing_pb2.py
i4t/protobuf/protobuf/Provisioning_pb2.py
i4t/protobuf/protobuf/Session_pb2.py
i4t/protobuf/protobuf/__init__.py
i4t/protobuf/protobuf/common_pb2.py
tests/__init__.py
tests/conftest.py
tests/test_instancing.py
tests/fixtures/__init__.py
tests/fixtures/pbwk.py
i4t-0.3.1.dist-info/LICENSE.txt
i4t-0.3.1.dist-info/METADATA
i4t-0.3.1.dist-info/WHEEL
i4t-0.3.1.dist-info/top_level.txt
i4t-0.3.1.dist-info/RECORD
